IUBBaseTools/ApiHandler.py
IUBBaseTools/FtpUploader.py
IUBBaseTools/IUBConfiguration.py
IUBBaseTools/Locker.py
IUBBaseTools/TorrentHandler.py
IUBBaseTools/UploadDb.py
IUBBaseTools/__init__.py
IUBBaseTools-0.0.7.dist-info/LICENSE
IUBBaseTools-0.0.7.dist-info/METADATA
IUBBaseTools-0.0.7.dist-info/WHEEL
IUBBaseTools-0.0.7.dist-info/top_level.txt
IUBBaseTools-0.0.7.dist-info/RECORD
